kelctl/__init__.py
kelctl/__main__.py
kelctl/configure.py
kelctl-0.0.2.dist-info/DESCRIPTION.rst
kelctl-0.0.2.dist-info/METADATA
kelctl-0.0.2.dist-info/RECORD
kelctl-0.0.2.dist-info/WHEEL
kelctl-0.0.2.dist-info/entry_points.txt
kelctl-0.0.2.dist-info/metadata.json
kelctl-0.0.2.dist-info/top_level.txt
