Metadata-Version: 2.0
Name: kelctl
Version: 0.0.2
Summary: kelctl
Home-page: UNKNOWN
Author: Eldarion, Inc.
Author-email: development@eldarion.com
License: Apache 2.0
Platform: UNKNOWN
Classifier: License :: OSI Approved :: Apache Software License
Classifier: Programming Language :: Python :: 3.5
Requires-Dist: Click (==6.6)
Requires-Dist: PyYAML (==3.11)
Requires-Dist: kel-cluster
Requires-Dist: requests (==2.9.1)
